streamlit_state_attribute/__init__.py
streamlit_state_attribute/state_attribute.py
streamlit_state_attribute/unique_attribute_missing_error.py
streamlit_state_attribute-0.2.3.dist-info/WHEEL
streamlit_state_attribute-0.2.3.dist-info/METADATA
streamlit_state_attribute-0.2.3.dist-info/RECORD
