Metadata-Version: 2.3
Name: streamlit-state-attribute
Version: 0.2.3
Summary: A lightweight utility to bind class attributes directly to Streamlit's session state, making it easy to persist and share values across reruns.
Keywords: streamlit,session state,state management,attributes,sync
Classifier: Development Status :: 3 - Alpha
Classifier: Intended Audience :: Developers
Classifier: License :: OSI Approved :: MIT License
Classifier: Programming Language :: Python
Classifier: Programming Language :: Python :: 3
Classifier: Programming Language :: Python :: 3.11
Classifier: Programming Language :: Python :: 3.12
Classifier: Programming Language :: Python :: 3.13
Classifier: Topic :: Software Development :: Libraries
Classifier: Topic :: Utilities
Requires-Dist: streamlit>=1.30.0
Requires-Python: >=3.11
